qstd_async_tools/__init__.py
qstd_async_tools/background.py
qstd_async_tools/call_limit.py
qstd_async_tools/call_limit_time.py
qstd_async_tools/gather.py
qstd_async_tools/shield.py
qstd_async_tools/trace.py
qstd_async_tools-0.3.0.dist-info/LICENSE
qstd_async_tools-0.3.0.dist-info/METADATA
qstd_async_tools-0.3.0.dist-info/WHEEL
qstd_async_tools-0.3.0.dist-info/top_level.txt
qstd_async_tools-0.3.0.dist-info/RECORD
