Metadata-Version: 2.1
Name: qstd-async-tools
Version: 0.3.0
Summary: Async tools
Home-page: https://github.com/QuisEgoSum/qstd-async-tools
Author: QuisEgoSum
Author-email: subbotin.evdokim@gmail.com
License: MIT
Keywords: asyncio
Requires-Python: >=3.7
License-File: LICENSE
